counter.sv
module counter #(
    parameter int WIDTH = 8
) (
    input logic clk,
    input logic rst,
    input logic en,
    output logic [WIDTH-1:0] count
);
  always_ff @(posedge clk, negedge rst) begin
    if (!rst) begin
      count <= 0;
    end else if (en) begin
      count <= count + 1;
    end

  end

endmodule

counter_tb.sv
`timescale 1ns / 1ps

module counter_tb;

  parameter int WIDTH = 4;

  logic clk;
  logic rst_n;
  logic enable;
  logic [WIDTH-1:0] count;

  // Instantiate the counter module
  counter #(
      .WIDTH(WIDTH)
  ) dut (
      .clk(clk),
      .rst(rst_n),
      .en(enable),
      .count(count)
  );

  // Clock generation
  initial begin
    clk = 0;
    forever #5 clk = ~clk;  // 100 MHz clock
  end

  // Test sequence
  initial begin
    // Initialize signals
    rst_n  = 0;
    enable = 0;

    // Apply reset
    #10 rst_n = 1;  // Release reset after 10 ns

    // Enable counting
    #10 enable = 1;  // Enable counting after another 10 ns

    // Wait for some time to observe counting
    #100;

    // Disable counting
    enable = 0;

    // Wait for some time to observe that counting has stopped
    #50;



    // Finish simulation
    $finish;
  end

  initial begin
    $timeformat(-9, 1, " ns", 8);
    $monitor("time=%t clk=%b rst=%b en=%b count=%2d", $time, clk, rst_n, enable, count);
    $dumpfile("counter_tb.vcd");
    $dumpvars(0, counter_tb);
  end

endmodule

counter_tb.vcd
$date
	Fri Apr 24 03:18:21 2026
$end
$version
	Icarus Verilog
$end
$timescale
	1ps
$end
$scope module counter_tb $end
$var wire 4 ! count [3:0] $end
$var reg 1 " clk $end
$var reg 1 # enable $end
$var reg 1 $ rst_n $end
$scope module dut $end
$var wire 1 " clk $end
$var wire 1 # en $end
$var wire 1 $ rst $end
$var reg 4 % count [3:0] $end
$upscope $end
$upscope $end
$enddefinitions $end
#0
$dumpvars
b0 %
0$
0#
0"
b0 !
$end
#5000
1"
#10000
0"
1$
#15000
1"
#20000
0"
1#
#25000
b1 !
b1 %
1"
#30000
0"
#35000
b10 !
b10 %
1"
#40000
0"
#45000
b11 !
b11 %
1"
#50000
0"
#55000
b100 !
b100 %
1"
#60000
0"
#65000
b101 !
b101 %
1"
#70000
0"
#75000
b110 !
b110 %
1"
#80000
0"
#85000
b111 !
b111 %
1"
#90000
0"
#95000
b1000 !
b1000 %
1"
#100000
0"
#105000
b1001 !
b1001 %
1"
#110000
0"
#115000
b1010 !
b1010 %
1"
#120000
0"
0#
